TOPSIS/__init__.py
TOPSIS/__main__.py
topsis_aayushi_102103676-1.2.0.dist-info/licenses/LICENSE
topsis_aayushi_102103676-1.2.0.dist-info/METADATA
topsis_aayushi_102103676-1.2.0.dist-info/WHEEL
topsis_aayushi_102103676-1.2.0.dist-info/entry_points.txt
topsis_aayushi_102103676-1.2.0.dist-info/top_level.txt
topsis_aayushi_102103676-1.2.0.dist-info/RECORD
