Metadata-Version: 2.4
Name: Topsis-Aayushi-102103676
Version: 1.2.0
Summary: A Python package to calculate TOPSIS scores and rank models.
Home-page: https://github.com/AayushiPuri/topsis
Author: Aayushi Puri
Author-email: meaayushipuri@gmail.com
License: MIT
Classifier: License :: OSI Approved :: MIT License
Classifier: Programming Language :: Python :: 3
Classifier: Programming Language :: Python :: 3.8
Classifier: Programming Language :: Python :: 3.9
Classifier: Programming Language :: Python :: 3.10
License-File: LICENSE
Requires-Dist: numpy
Requires-Dist: pandas
Dynamic: author
Dynamic: author-email
Dynamic: classifier
Dynamic: description
Dynamic: description-content-type
Dynamic: home-page
Dynamic: license
Dynamic: license-file
Dynamic: requires-dist
Dynamic: summary
